.appveyor.yml
.bumpversion.cfg
.cookiecutterrc
.coveragerc
.editorconfig
.pre-commit-config.yaml
.readthedocs.yml
.travis.yml
AUTHORS.rst
CHANGELOG.rst
CONTRIBUTING.rst
LICENSE
MANIFEST.in
README.rst
setup.cfg
setup.py
tox.ini
ci/bootstrap.py
ci/requirements.txt
ci/templates/.appveyor.yml
ci/templates/.travis.yml
docs/authors.rst
docs/changelog.rst
docs/conf.py
docs/contributing.rst
docs/index.rst
docs/installation.rst
docs/readme.rst
docs/requirements.txt
docs/spelling_wordlist.txt
docs/usage.rst
docs/reference/cleandata.rst
docs/reference/index.rst
src/cleandata/__init__.py
src/cleandata/__main__.py
src/cleandata/cli.py
src/cleandata.egg-info/PKG-INFO
src/cleandata.egg-info/SOURCES.txt
src/cleandata.egg-info/dependency_links.txt
src/cleandata.egg-info/entry_points.txt
src/cleandata.egg-info/not-zip-safe
src/cleandata.egg-info/top_level.txt
tests/test_cleandata.py