Metadata-Version: 1.2
Name: cleandata
Version: 0.0.0
Summary: An example package. Generated with cookiecutter-pylibrary.
Home-page: https://github.com/rinman24/cleandata
Author: Richard Headen Inman
Author-email: rinman24@gmail.com
License: MIT
Project-URL: Documentation, https://cleandata.readthedocs.io/
Project-URL: Changelog, https://cleandata.readthedocs.io/en/latest/changelog.html
Project-URL: Issue Tracker, https://github.com/rinman24/cleandata/issues
Platform: UNKNOWN
Classifier: Development Status :: 5 - Production/Stable
Classifier: Intended Audience :: Developers
Classifier: License :: OSI Approved :: MIT License
Classifier: Operating System :: Unix
Classifier: Operating System :: POSIX
Classifier: Operating System :: Microsoft :: Windows
Classifier: Programming Language :: Python
Classifier: Programming Language :: Python :: 3
Classifier: Programming Language :: Python :: 3 :: Only
Classifier: Programming Language :: Python :: 3.6
Classifier: Programming Language :: Python :: 3.7
Classifier: Programming Language :: Python :: 3.8
Classifier: Programming Language :: Python :: 3.9
Classifier: Programming Language :: Python :: Implementation :: CPython
Classifier: Programming Language :: Python :: Implementation :: PyPy
Classifier: Topic :: Utilities
Requires-Python: >=3.6
